README.md
pyproject.toml
setup.py
examples/__init__.py
examples/demo.py
examples/demo_embedding.py
examples/demo_graph.py
tb_chainer/__init__.py
tb_chainer/crc32c.py
tb_chainer/embedding.py
tb_chainer/event_file_writer.py
tb_chainer/graph.py
tb_chainer/name_scope.py
tb_chainer/ordered_set.py
tb_chainer/record_writer.py
tb_chainer/summary.py
tb_chainer/utils.py
tb_chainer/writer.py
tb_chainer/src/__init__.py
tb_chainer/src/attr_value_pb2.py
tb_chainer/src/event_pb2.py
tb_chainer/src/graph_pb2.py
tb_chainer/src/node_def_pb2.py
tb_chainer/src/resource_handle_pb2.py
tb_chainer/src/summary_pb2.py
tb_chainer/src/tensor_pb2.py
tb_chainer/src/tensor_shape_pb2.py
tb_chainer/src/types_pb2.py
tb_chainer/src/versions_pb2.py
tensorboard_chainer.egg-info/PKG-INFO
tensorboard_chainer.egg-info/SOURCES.txt
tensorboard_chainer.egg-info/dependency_links.txt
tensorboard_chainer.egg-info/not-zip-safe
tensorboard_chainer.egg-info/requires.txt
tensorboard_chainer.egg-info/top_level.txt