Metadata-Version: 2.1
Name: tensorboard-chainer
Version: 0.5.3
Summary: Log TensorBoard events with chainer
Home-page: https://github.com/neka-nat/tensorboard-chainer
Author: nake nat
Author-email: nakanat.stock@gmail.com
License: MIT license
Platform: UNKNOWN
